README.txt
setup.cfg
setup.py
roNNie.egg-info/PKG-INFO
roNNie.egg-info/SOURCES.txt
roNNie.egg-info/dependency_links.txt
roNNie.egg-info/requires.txt
roNNie.egg-info/top_level.txt
ronnie/LICENSE.txt
ronnie/__init__.py
ronnie/meta.py
ronnie/rManager.py
ronnie.egg-info/PKG-INFO
ronnie.egg-info/SOURCES.txt
ronnie.egg-info/dependency_links.txt
ronnie.egg-info/requires.txt
ronnie.egg-info/top_level.txt
ronnie/conf/__init__.py
ronnie/conf/cnnCfg.py
ronnie/conf/logConf.json
ronnie/data/__init__.py
ronnie/data/digitalRec/test.zip
ronnie/data/digitalRec/train.zip
ronnie/examples/__init__.py
ronnie/examples/digitalr.py
ronnie/lib/__init__.py
ronnie/lib/util.py
ronnie/lib/collector/__init__.py
ronnie/lib/collector/cifaCollector.py
ronnie/lib/collector/drCollector.py
ronnie/lib/designer/__init__.py
ronnie/lib/monitor/__init__.py
ronnie/lib/monitor/custError.py
ronnie/lib/monitor/logKeeper.py
ronnie/lib/monitor/plottor.py
ronnie/lib/optimizer/CNNModel.py
ronnie/lib/optimizer/__init__.py
ronnie/logs/__init__.py
ronnie/template/__init__.py
ronnie/template/cnn.template
ronnie/template/cnn/c0p0d1.py
ronnie/template/cnn/c0p0d2.py
ronnie/template/cnn/c0p1d1.py
ronnie/template/cnn/c0p1d2.py
ronnie/template/cnn/c1p0d1.py
ronnie/template/cnn/c1p0d2.py
ronnie/template/cnn/c1p1d1.py
ronnie/template/cnn/c1p1d2.py
ronnie/template/cnn/c1p2d1.py
ronnie/template/cnn/c1p2d2.py
ronnie/template/cnn/c2p0d1.py
ronnie/template/cnn/c2p0d2.py
ronnie/template/cnn/c2p1d1.py
ronnie/template/cnn/c2p1d2.py
ronnie/template/cnn/c2p2d1.py
ronnie/template/cnn/c2p2d2.py
ronnie/template/cnn/cnnCfg.py