Metadata-Version: 1.2
Name: ronnie
Version: 1.0.8
Summary: roNNie. A Lightweight AI Framework for Deep Learning.
Home-page: https://ronnie.ai
Author: Kevin Lok KaWing
Author-email: kevinkwlok@gmail.com
License: MIT License
Keywords: AI,DeepLearning,CNN
Platform: UNKNOWN
Classifier: Development Status :: 4 - Beta
Classifier: Topic :: Scientific/Engineering :: Artificial Intelligence
Classifier: License :: OSI Approved :: MIT License
Requires-Python: >=3.6, <4
